pip_package_test/__init__.py
pip_package_test-0.0.1.dist-info/LICENSE.txt
pip_package_test-0.0.1.dist-info/METADATA
pip_package_test-0.0.1.dist-info/WHEEL
pip_package_test-0.0.1.dist-info/top_level.txt
pip_package_test-0.0.1.dist-info/RECORD
